Metadata-Version: 2.1
Name: modeldeploy-proxy-lib
Version: 0.2.1
Summary: The lib for modeldeploy-proxy.
Author: ever cheng
Author-email: ever_cheng@asus.com
License: Apache License Version 2.0
Requires-Python: >=3.6.0
Provides-Extra: dev
